campbell/__init__.py
campbell-0.1.0.dist-info/WHEEL
campbell-0.1.0.dist-info/METADATA
campbell-0.1.0.dist-info/RECORD
