Metadata-Version: 2.1
Name: campbell
Version: 0.1.0
Summary: Dataframe visualization on jupyter
Author: horoiwa
Author-email: horoiwa195@gmail.com
Requires-Python: >=3.7,<4.0
Classifier: Programming Language :: Python :: 3
Classifier: Programming Language :: Python :: 3.7
Classifier: Programming Language :: Python :: 3.8
